tele_muninn/__init__.py
tele_muninn/bot.py
tele_muninn/console.py
tele_muninn/greetings.py
tele_muninn/py.typed
tele_muninn-0.0.3.dist-info/entry_points.txt
tele_muninn-0.0.3.dist-info/WHEEL
tele_muninn-0.0.3.dist-info/METADATA
tele_muninn-0.0.3.dist-info/RECORD
