Metadata-Version: 2.1
Name: tele-muninn
Version: 0.0.3
Summary: Just like Alfred but for Telegram
Home-page: https://namuan.github.io/tele-muninn
License: MIT
Author: Namuan
Author-email: github@deskriders.dev
Requires-Python: >=3.7.1,<4.0
Classifier: Development Status :: 4 - Beta
Classifier: Intended Audience :: Developers
Classifier: License :: OSI Approved :: MIT License
Classifier: Operating System :: OS Independent
Classifier: Programming Language :: Python
Classifier: Programming Language :: Python :: 3
Classifier: Programming Language :: Python :: 3.10
Classifier: Programming Language :: Python :: 3.7
Classifier: Programming Language :: Python :: 3.8
Classifier: Programming Language :: Python :: 3.9
Classifier: Topic :: Software Development :: Libraries :: Python Modules
Classifier: Typing :: Typed
Requires-Dist: python-dotenv
Requires-Dist: python-telegram-bot
Requires-Dist: requests
Project-URL: Documentation, https://namuan.github.io/tele-muninn
Project-URL: Repository, https://github.com/namuan/tele-muninn
